LICENSE
MANIFEST.in
README.md
pyproject.toml
setup.py
lorann/clustering.h
lorann/lorann.h
lorann/lorann_base.h
lorann/lorann_fp.h
lorann/lorann_quant.h
lorann/quant.h
lorann/serialization.h
lorann/utils.h
lorann/Eigen/AccelerateSupport
lorann/Eigen/Cholesky
lorann/Eigen/CholmodSupport
lorann/Eigen/Core
lorann/Eigen/Dense
lorann/Eigen/Eigen
lorann/Eigen/Eigenvalues
lorann/Eigen/Geometry
lorann/Eigen/Householder
lorann/Eigen/IterativeLinearSolvers
lorann/Eigen/Jacobi
lorann/Eigen/KLUSupport
lorann/Eigen/LU
lorann/Eigen/MetisSupport
lorann/Eigen/OrderingMethods
lorann/Eigen/PaStiXSupport
lorann/Eigen/PardisoSupport
lorann/Eigen/QR
lorann/Eigen/QtAlignedMalloc
lorann/Eigen/SPQRSupport
lorann/Eigen/SVD
lorann/Eigen/Sparse
lorann/Eigen/SparseCholesky
lorann/Eigen/SparseCore
lorann/Eigen/SparseLU
lorann/Eigen/SparseQR
lorann/Eigen/StdDeque
lorann/Eigen/StdList
lorann/Eigen/StdVector
lorann/Eigen/SuperLUSupport
lorann/Eigen/ThreadPool
lorann/Eigen/UmfPackSupport
lorann/Eigen/Version
lorann/Eigen/src/AccelerateSupport/AccelerateSupport.h
lorann/Eigen/src/AccelerateSupport/InternalHeaderCheck.h
lorann/Eigen/src/Cholesky/InternalHeaderCheck.h
lorann/Eigen/src/Cholesky/LDLT.h
lorann/Eigen/src/Cholesky/LLT.h
lorann/Eigen/src/Cholesky/LLT_LAPACKE.h
lorann/Eigen/src/CholmodSupport/CholmodSupport.h
lorann/Eigen/src/CholmodSupport/InternalHeaderCheck.h
lorann/Eigen/src/Core/ArithmeticSequence.h
lorann/Eigen/src/Core/Array.h
lorann/Eigen/src/Core/ArrayBase.h
lorann/Eigen/src/Core/ArrayWrapper.h
lorann/Eigen/src/Core/Assign.h
lorann/Eigen/src/Core/AssignEvaluator.h
lorann/Eigen/src/Core/Assign_MKL.h
lorann/Eigen/src/Core/BandMatrix.h
lorann/Eigen/src/Core/Block.h
lorann/Eigen/src/Core/CommaInitializer.h
lorann/Eigen/src/Core/ConditionEstimator.h
lorann/Eigen/src/Core/CoreEvaluators.h
lorann/Eigen/src/Core/CoreIterators.h
lorann/Eigen/src/Core/CwiseBinaryOp.h
lorann/Eigen/src/Core/CwiseNullaryOp.h
lorann/Eigen/src/Core/CwiseTernaryOp.h
lorann/Eigen/src/Core/CwiseUnaryOp.h
python/lorann.egg-info/PKG-INFO
python/lorann.egg-info/SOURCES.txt
python/lorann.egg-info/dependency_links.txt
python/lorann.egg-info/not-zip-safe
python/lorann.egg-info/requires.txt
python/lorann.egg-info/top_level.txt
